aiorqlite/__init__.py
aiorqlite/_ephemeral.py
aiorqlite/connections.py
aiorqlite/constants.py
aiorqlite/cursors.py
aiorqlite/dbapi2.py
aiorqlite/exceptions.py
aiorqlite/extensions.py
aiorqlite/row.py
aiorqlite/types.py
AIOrqlite-0.2.3.dist-info/LICENSE
AIOrqlite-0.2.3.dist-info/METADATA
AIOrqlite-0.2.3.dist-info/WHEEL
AIOrqlite-0.2.3.dist-info/top_level.txt
AIOrqlite-0.2.3.dist-info/RECORD
