Metadata-Version: 2.1
Name: AIOrqlite
Version: 0.2.3
Summary: Ayncio-based Python client for rqlite.
Home-page: https://github.com/superloach/aiorqlite
Author: Terra Brown
Author-email: superloach42@gmail.com
License: UNKNOWN
Platform: UNKNOWN
Classifier: Programming Language :: Python :: 3
Classifier: License :: OSI Approved :: MIT License
Classifier: Operating System :: OS Independent
